distributed_nose/__init__.py
distributed_nose/plugin.py
distributed_nose-1.2.0.dist-info/AUTHORS
distributed_nose-1.2.0.dist-info/LICENSE
distributed_nose-1.2.0.dist-info/METADATA
distributed_nose-1.2.0.dist-info/WHEEL
distributed_nose-1.2.0.dist-info/entry_points.txt
distributed_nose-1.2.0.dist-info/top_level.txt
distributed_nose-1.2.0.dist-info/RECORD
