Metadata-Version: 2.1
Name: distributed-nose
Version: 1.2.0
Summary: Distribute your nose tests across multiple machines, hassle-free
Home-page: http://policystat.github.com/distributed-nose
Author: Wes Winham
Author-email: winhamwr@gmail.com
License: BSD
Platform: any
Classifier: Development Status :: 4 - Beta
Classifier: Intended Audience :: Developers
Classifier: License :: OSI Approved :: BSD License
Classifier: Topic :: Software Development
Classifier: Programming Language :: Python
Classifier: Programming Language :: Python :: 2.6
Classifier: Programming Language :: Python :: 2.7
Classifier: Programming Language :: Python :: 3.3
Classifier: Operating System :: OS Independent
Classifier: Operating System :: POSIX
Classifier: Operating System :: Microsoft :: Windows
Classifier: Operating System :: MacOS :: MacOS X
Requires-Dist: nose
Requires-Dist: hashring
